[
  {
    "name": "theme_info",
    "theme_name": "Blockshop",
    "theme_author": "Troop Themes",
    "theme_version": "9.1.0",
    "theme_documentation_url": "https:\/\/support.troopthemes.com\/guide\/getting-started\/",
    "theme_support_url": "http:\/\/support.troopthemes.com\/"
  },
  {
    "name": "Colors",
    "settings": [
      {
        "type": "header",
        "content": "General"
      },
      {
        "id": "color--accent-1",
        "label": "Accent 1",
        "type": "color",
        "default": "#fff4cc"
      },
      {
        "id": "color--accent-2",
        "label": "Accent 2",
        "type": "color",
        "default": "#fff4cc"
      },
      {
        "id": "bg-color--light",
        "label": "Light background",
        "type": "color",
        "default": "#f7f7f7"
      },
      {
        "id": "bg-color--dark",
        "label": "Dark background",
        "type": "color",
        "default": "#222222"
      },
      {
        "type": "color",
        "id": "bg-color--body",
        "label": "Page background",
        "default": "#ffffff"
      },
      {
        "type": "color",
        "id": "color--body",
        "label": "Text",
        "default": "#444444"
      },
      {
        "type": "color",
        "id": "color--alternative",
        "label": "Light text",
        "default": "#ffffff",
        "info": "Commonly used for text over images"
      },
      {
        "type": "color",
        "id": "color--button",
        "label": "Button text",
        "default": "#ffffff"
      },
      {
        "type": "color",
        "id": "bg-color--button",
        "label": "Button background",
        "default": "#444444"
      },
      {
        "type": "textarea",
        "id": "color--swatches",
        "label": "Color swatch configuration",
        "default": "yellow green: #9acd32\nRed: rgb(139,0,0)\norange: orange.PNG\nStealth Grey: stealth-grey.jpg",
        "info": "Each rule must be its own line. [Learn more](https:\/\/support.troopthemes.com\/guide\/color-swatch-guide) about naming conventions."
      }
    ]
  },
  {
    "name": "Typography",
    "settings": [
      {
        "type": "header",
        "content": "Headings"
      },
      {
        "id": "typography--heading",
        "label": "Font",
        "type": "font_picker",
        "default": "karla_n7"
      },
      {
        "id": "typography--heading--uppercase",
        "label": "Uppercase",
        "type": "checkbox",
        "default": false
      },
      {
        "id": "typography--heading--size",
        "label": "Size",
        "type": "select",
        "options": [
          {
            "label": "Extra Large",
            "value": "x-large"
          },
          {
            "label": "Large",
            "value": "large"
          },
          {
            "label": "Medium",
            "value": "medium"
          },
          {
            "label": "Small",
            "value": "small"
          }
        ],
        "default": "medium"
      },
      {
        "type": "header",
        "content": "Navigation and buttons"
      },
      {
        "id": "typography--accent",
        "label": "Font",
        "type": "font_picker",
        "default": "roboto_n4"
      },
      {
        "type": "header",
        "content": "Paragraphs"
      },
      {
        "id": "typography--paragraph",
        "label": "Font",
        "type": "font_picker",
        "default": "roboto_n4"
      },
      {
        "id": "typography--paragraph--size",
        "label": "Size",
        "type": "select",
        "options": [
          {
            "label": "Large",
            "value": "large"
          },
          {
            "label": "Medium",
            "value": "medium"
          },
          {
            "label": "Small",
            "value": "small"
          }
        ],
        "default": "medium"
      }
    ]
  },
  {
    "name": "Product grid",
    "settings": [
      {
        "id": "product--image-size",
        "label": "Image size",
        "type": "select",
        "options": [
          {
            "label": "Natural",
            "value": "natural"
          },
          {
            "label": "Square (1:1)",
            "value": "square"
          },
          {
            "label": "Landscape (4:3)",
            "value": "landscape"
          },
          {
            "label": "Portrait (2:3)",
            "value": "portrait"
          }
        ],
        "default": "portrait"
      },
      {
        "type": "checkbox",
        "id": "product--hover-image-enabled",
        "label": "Enable hover image",
        "default": false,
        "info": "This will use its second image. You can reorder images in the product's admin page."
      },
      {
        "type": "checkbox",
        "id": "product--show-vendor",
        "label": "Show vendor name",
        "default": false,
        "info": "e.g. Shopify, Apple"
      },
      {
        "type": "checkbox",
        "id": "product--show-rating",
        "label": "Show product rating",
        "default": false,
        "info": "To display a rating, add a product rating app. [Learn more](https:\/\/help.shopify.com\/en\/manual\/products\/product-reviews)"
      },
      {
        "type": "checkbox",
        "id": "product--swatches-enabled",
        "label": "Enable color swatches",
        "default": false,
        "info": "Display color swatches when available. [Learn more](https:\/\/support.troopthemes.com\/guide\/color-swatch-guide)"
      },
      {
        "id": "product--text-alignment",
        "label": "Text alignment",
        "type": "select",
        "options": [
          {
            "label": "Left",
            "value": "left"
          },
          {
            "label": "Center",
            "value": "center"
          }
        ],
        "default": "left"
      },
      {
        "type": "header",
        "content": "Product labels",
        "info": "New, sale, out of stock, featured tags"
      },
      {
        "id": "product--label-shape",
        "label": "Label shape",
        "type": "select",
        "options": [
          {
            "label": "Square",
            "value": "square"
          },
          {
            "label": "Round",
            "value": "round"
          }
        ],
        "default": "round"
      },
      {
        "id": "product--label-color",
        "label": "Label color",
        "type": "select",
        "options": [
          {
            "label": "None",
            "value": "none"
          },
          {
            "label": "Light",
            "value": "light"
          },
          {
            "label": "Dark",
            "value": "dark"
          },
          {
            "label": "Accent 1",
            "value": "accent-1"
          },
          {
            "label": "Accent 2",
            "value": "accent-2"
          }
        ],
        "default": "light"
      },
      {
        "id": "product--label-light-text",
        "label": "Use light text color",
        "type": "checkbox",
        "default": false
      },
      {
        "id": "product--show-sale-label",
        "label": "Sale label",
        "type": "select",
        "options": [
          {
            "label": "Don't show",
            "value": "false"
          },
          {
            "label": "Show text",
            "value": "show-text"
          },
          {
            "label": "Show percent off",
            "value": "show-percent"
          }
        ],
        "default": "show-text"
      },
      {
        "type": "checkbox",
        "id": "product--show-new-label",
        "label": "Show new label",
        "default": true
      },
      {
        "label": "New label period",
        "id": "product--new-label-period",
        "type": "range",
        "min": 1,
        "max": 90,
        "step": 1,
        "default": 90,
        "info": "Number of days shown"
      },
      {
        "id": "product--featured-tags",
        "label": "Featured tags",
        "type": "textarea",
        "placeholder": "Limited edition, Sustainable, Organic",
        "default": "Limited edition, Sustainable, Organic",
        "info": "[Learn more](https:\/\/support.troopthemes.com\/guide\/configuring-product-labels\/)"
      },
      {
        "type": "header",
        "content": "Quick add"
      },
      {
        "type": "checkbox",
        "id": "product--quick-add-enabled",
        "label": "Show quick add buttons",
        "default": true
      },
      {
        "type": "select",
        "id": "product--variant-style",
        "label": "Product variant style",
        "options": [
          {
            "label": "Dropdowns",
            "value": "dropdowns"
          },
          {
            "label": "Buttons",
            "value": "buttons"
          }
        ],
        "default": "dropdowns"
      },
      {
        "type": "checkbox",
        "id": "product--show-quantity",
        "label": "Show quantity selector",
        "default": false
      }
    ]
  },
  {
    "name": "Search",
    "settings": [
      {
        "type": "checkbox",
        "id": "search--show-in-header",
        "label": "Show in header and mobile menu",
        "default": true
      },
      {
        "id": "search--list-heading",
        "label": "List heading",
        "type": "text",
        "default": "Popular searches"
      },
      {
        "type": "link_list",
        "id": "search--list",
        "label": "Default list"
      },
      {
        "type": "checkbox",
        "id": "search--show-products",
        "label": "Show popular products",
        "default": true
      },
      {
        "id": "search--product-heading",
        "label": "Popular product heading",
        "type": "text",
        "default": "Popular products"
      },
      {
        "type": "product_list",
        "id": "search--product-list",
        "label": "Popular products",
        "limit": 4,
        "info": "If left blank will be populated with the most sold products."
      }
    ]
  },
  {
    "name": "Popup",
    "settings": [
      {
        "type": "checkbox",
        "id": "popup--enabled",
        "label": "Enable",
        "default": false
      },
      {
        "label": "Test mode",
        "type": "checkbox",
        "id": "popup--test-mode",
        "default": false,
        "info": "Enable to view popup on each page load"
      },
      {
        "type": "image_picker",
        "id": "popup--image",
        "label": "Image",
        "info": "Recommended 600px wide and 1200px wide when only showing image"
      },
      {
        "type": "url",
        "id": "popup--image-url",
        "label": "Link to"
      },
      {
        "type": "page",
        "id": "popup--page-content",
        "label": "Page content"
      },
      {
        "type": "checkbox",
        "id": "popup--newsletter--enabled",
        "label": "Show newsletter form",
        "default": true
      },
      {
        "type": "text",
        "id": "popup--newsletter--heading",
        "label": "Heading",
        "default": "Get the scoop on new arrivals, special promos and sales."
      },
      {
        "type": "checkbox",
        "id": "popup--social--enabled",
        "label": "Show social icons",
        "default": true
      },
      {
        "label": "Show in (seconds)",
        "id": "popup--seconds-range",
        "type": "range",
        "min": 1,
        "max": 10,
        "step": 1,
        "default": 3
      },
      {
        "label": "Show again after (days)",
        "id": "popup--days-range",
        "type": "range",
        "min": 1,
        "max": 30,
        "step": 1,
        "default": 7,
        "info": "Independent to each browser and device"
      }
    ]
  },
  {
    "name": "Favicon",
    "settings": [
      {
        "type": "image_picker",
        "id": "favicon",
        "label": "Icon",
        "info": "Will be scaled down to 32 x 32px"
      }
    ]
  },
  {
    "name": "Blog",
    "settings": [
      {
        "id": "hide-tags",
        "label": "Hide tags from tag filter",
        "type": "text",
        "default": "featured, pinned",
        "placeholder": "featured, pinned",
        "info": "Use a comma to separate"
      }
    ]
  },
  {
    "name": "Cart page",
    "settings": [
      {
        "type": "select",
        "id": "cart--type",
        "label": "Cart type",
        "options": [
          {
            "value": "page",
            "label": "Page"
          },
          {
            "value": "drawer",
            "label": "Drawer"
          }
        ],
        "default": "drawer"
      },
      {
        "type": "checkbox",
        "id": "cart--show-note",
        "label": "Enable order notes",
        "default": true
      }
    ]
  },
  {
    "name": "Social media",
    "settings": [
      {
        "type": "text",
        "id": "social--instagram--url",
        "label": "Instagram",
        "info": "https:\/\/instagram.com\/shopify"
      },
      {
        "type": "text",
        "id": "social--facebook--url",
        "label": "Facebook",
        "info": "https:\/\/www.facebook.com\/shopify"
      },
      {
        "type": "text",
        "id": "social--youtube--url",
        "label": "Youtube",
        "info": "https:\/\/www.youtube.com\/user\/shopify"
      },
      {
        "type": "text",
        "id": "social--vimeo--url",
        "label": "Vimeo",
        "info": "https:\/\/vimeo.com\/shopify"
      },
      {
        "type": "text",
        "id": "social--pinterest--url",
        "label": "Pinterest",
        "info": "https:\/\/www.pinterest.com\/shopify"
      },
      {
        "type": "text",
        "id": "social--twitter--url",
        "label": "Twitter",
        "info": "https:\/\/twitter.com\/shopify"
      },
      {
        "type": "text",
        "id": "social--tiktok--url",
        "label": "TikTok",
        "info": "https:\/\/tiktok.com\/@shopify"
      }
    ]
  }
]